Workbook
Name Acc1_Sta: [1]Values!$D$2:$D$4
Name Boolean: [2]!Table4[Boolean]
Name ClientCodes: [2]!Table1[Client Code]
Name Doc1_Ref: [1]Values!$A$2:$A$24
Name Environment_Type: [2]!Table6[Environment]
Name Fee1_Cat: [1]Values!$B$2:$B$7
Name Fee1_Sta: [1]Values!$C$2:$C$7
Name Maintenance_Status: [2]!Table5[Maintenance Status]
Name Network_Dev_Type: [2]!Table8[Network Dev Type]
Name Pro_Nam: [1]Values!$E$2:$E$29
Name Status: [3]Constants!$A$2:$A$5

Sheet Applications Basic Data
A1: Applicatio ID | B1: Main application | C1: Sub application | D1: Description | E1: Active | F1: Technical Support group | G1: Approval group | H1: IT Application owner | I1: Corp. | J1: Comment | K1: OK?
A2: 1 | B2: My TimeTrack | C2: My TimeTrack | D2: Time management system | E2: YES | F2: GBB_ORG_TMM | G2: APP_ORG_TMM | H2: Carl Smith | I2: YES | J2: Ongoing project to push it to the cloud | K2: OK
A3: 2 | B3: WarehousePlus | C3: WarehousePlus-Facilities | D3: Warehouse management system | E3: YES | F3: GBB_ORB_LOG | G3: APP_ORG_LOG | H3: Stanley Rice | I3: YES | J3: To be decomissioned in 2024 | K3: OK
A4: 3 | B4: WarehousePlus | C4: WarehousePlus-Promotions | D4: Warehouse management system | E4: YES | F4: GBB_ORB_LOG | G4: APP_ORG_LOG | H4: Stanley Rice | I4: YES | J4: To be decomissioned in 2024 | K4: OK
A5: 4 | B5: WarehousePlus | C5: WarehousePlus-IT | D5: Warehouse management system | E5: YES | F5: GBB_ORB_LOG | G5: APP_ORG_LOG | H5: Stanley Rice | I5: YES | J5: To be decomissioned in 2024 | K5: OK
A6: 5 | B6: WarehousePlus | C6: WarehousePlus-Lease | D6: Warehouse management system | E6: YES | F6: GBB_ORB_LOG | G6: APP_ORG_LOG | H6: Stanley Rice | I6: YES | J6: To be decomissioned in 2024 | K6: OK
A7: 6 | B7: FinanceFast | C7: FinanceFast | D7: Execution System for FinanceFast | E7: YES | F7: GBB_ORG_FNC | G7: APP_ORG_FNC | H7: Austin Buck | I7: YES | K7: OK
A8: 7 | B8: PayRoll Automation | C8: PayRoll Automation | D8: Payroll interface software | E8: YES | F8: GBB_ORG_PYR | G8: APP_ORG_PYR | H8: Julie Armitage | I8: YES | K8: OK
A9: 8 | B9: Credit Check | C9: Credit Check | D9: Software to perform credit check operations | E9: YES | F9: GBB_ORG_CHK | G9: APP_ORG_CHK | H9: Elly Fuller | I9: YES | K9: OK
A10: 9 | B10: Travel Manager | C10: Travel Manager | D10: Travel budget approval system | E10: YES | F10: GBB_ORG_TRV | G10: APP_ORG_TRV | H10: Edgar Bowes | I10: YES | K10: OK
A11: 10 | B11: HolidayPlanner | C11: HolidayPlanner | D11: Team holidays planner and approval in-house system | E11: YES | F11: GBB_ORG_HOL | G11: APP_ORG_HOL | H11: Gillian Reynolds | I11: NO | K11: OK

Sheet Business Processes
T1: 3 | U1: 4 | V1: 5 | W1: 6 | X1: 7 | Y1: 8 | Z1: 9 | AA1: 10 | AB1: 2
A2: Application ID | B2: Main application | C2: Sub application | D2: Classification | E2: Support | F2: Knowledge | G2: Satisfaction | H2: Usage | I2: UK | J2: BE | K2: IT | L2: FR | M2: PT | N2: CH | O2: NL | P2: IR | Q2: ES | R2: Total | T2: ES | U2: UK | V2: BE | W2: CH | X2: IT | Y2: IR | Z2: PT | AA2: NL | AB2: FR
A3: 1 | B3: My TimeTrack | C3: My TimeTrack | D3: Time Management | E3: My TimeTrack Group | F3: High | G3: High | H3: High | I3: 1 | K3: 1 | L3: 1 | N3: 1 | R3: =SUM(I3:Q3) -> 4 | T3: =IF(Q3=1,VLOOKUP($E3,'Group members'!$A$2:$J$4,'Business Processes'!T$1,FALSE),"") | U3: =IF(I3=1,VLOOKUP($E3,'Group members'!$A$2:$J$4,'Business Processes'!U$1,FALSE),"") -> John Anderson | V3: =IF(J3=1,VLOOKUP($E3,'Group members'!$A$2:$J$4,'Business Processes'!V$1,FALSE),"") | W3: =IF(N3=1,VLOOKUP($E3,'Group members'!$A$2:$J$4,'Business Processes'!W$1,FALSE),"") -> Michael Fowkes | X3: =IF(K3=1,VLOOKUP($E3,'Group members'!$A$2:$J$4,'Business Processes'!X$1,FALSE),"") -> Luigi Pennini | Y3: =IF(P3=1,VLOOKUP($E3,'Group members'!$A$2:$J$4,'Business Processes'!Y$1,FALSE),"") | Z3: =IF(M3=1,VLOOKUP($E3,'Group members'!$A$2:$J$4,'Business Processes'!Z$1,FALSE),"") | AA3: =IF(O3=1,VLOOKUP($E3,'Group members'!$A$2:$J$4,'Business Processes'!AA$1,FALSE),"") | AB3: =IF(L3=1,VLOOKUP($E3,'Group members'!$A$2:$J$8,'Business Processes'!AB$1,FALSE),"") -> Anne-Marie Lavigne
A4: 2 | B4: WarehousePlus | C4: WarehousePlus-Facilities | D4: Warehouse Management | E4: WarehousePlus Group | F4: High | G4: Medium | H4: High | I4: 1 | L4: 1 | M4: 1 | O4: 1 | P4: 1 | Q4: 1 | R4: =SUM(I4:Q4) -> 6 | T4: =IF(Q4=1,VLOOKUP($E4,'Group members'!$A$2:$J$4,'Business Processes'!T$1,FALSE),"") -> Lourdes García | U4: =IF(I4=1,VLOOKUP($E4,'Group members'!$A$2:$J$4,'Business Processes'!U$1,FALSE),"") -> Mary Johnson, Liam Chambers | V4: =IF(J4=1,VLOOKUP($E4,'Group members'!$A$2:$J$4,'Business Processes'!V$1,FALSE),"") | W4: =IF(N4=1,VLOOKUP($E4,'Group members'!$A$2:$J$4,'Business Processes'!W$1,FALSE),"") | X4: =IF(K4=1,VLOOKUP($E4,'Group members'!$A$2:$J$4,'Business Processes'!X$1,FALSE),"") | Y4: =IF(P4=1,VLOOKUP($E4,'Group members'!$A$2:$J$4,'Business Processes'!Y$1,FALSE),"") -> Ann Lewis | Z4: =IF(M4=1,VLOOKUP($E4,'Group members'!$A$2:$J$4,'Business Processes'!Z$1,FALSE),"") -> Fernando Henriques | AA4: =IF(O4=1,VLOOKUP($E4,'Group members'!$A$2:$J$4,'Business Processes'!AA$1,FALSE),"") -> Ronald de Wit | AB4: =IF(L4=1,VLOOKUP($E4,'Group members'!$A$2:$J$8,'Business Processes'!AB$1,FALSE),"") -> Jean-Christophe Moulin
A5: 3 | B5: WarehousePlus | C5: WarehousePlus-Promotions | D5: Warehouse Management | E5: WarehousePlus Group | F5: Low | G5: Medium | H5: Medium | I5: 1 | J5: 1 | L5: 1 | O5: 1 | R5: =SUM(I5:Q5) -> 4 | T5: =IF(Q5=1,VLOOKUP($E5,'Group members'!$A$2:$J$4,'Business Processes'!T$1,FALSE),"") | U5: =IF(I5=1,VLOOKUP($E5,'Group members'!$A$2:$J$4,'Business Processes'!U$1,FALSE),"") -> Mary Johnson, Liam Chambers | V5: =IF(J5=1,VLOOKUP($E5,'Group members'!$A$2:$J$4,'Business Processes'!V$1,FALSE),"") -> Jaco Van Dijk | W5: =IF(N5=1,VLOOKUP($E5,'Group members'!$A$2:$J$4,'Business Processes'!W$1,FALSE),"") | X5: =IF(K5=1,VLOOKUP($E5,'Group members'!$A$2:$J$4,'Business Processes'!X$1,FALSE),"") | Y5: =IF(P5=1,VLOOKUP($E5,'Group members'!$A$2:$J$4,'Business Processes'!Y$1,FALSE),"") | Z5: =IF(M5=1,VLOOKUP($E5,'Group members'!$A$2:$J$4,'Business Processes'!Z$1,FALSE),"") | AA5: =IF(O5=1,VLOOKUP($E5,'Group members'!$A$2:$J$4,'Business Processes'!AA$1,FALSE),"") -> Ronald de Wit | AB5: =IF(L5=1,VLOOKUP($E5,'Group members'!$A$2:$J$8,'Business Processes'!AB$1,FALSE),"") -> Jean-Christophe Moulin
A6: 4 | B6: WarehousePlus | C6: WarehousePlus-IT | D6: Warehouse Management | E6: WarehousePlus Group | F6: Medium | G6: Medium | H6: High | I6: 1 | K6: 1 | O6: 1 | P6: 1 | R6: =SUM(I6:Q6) -> 4 | T6: =IF(Q6=1,VLOOKUP($E6,'Group members'!$A$2:$J$4,'Business Processes'!T$1,FALSE),"") | U6: =IF(I6=1,VLOOKUP($E6,'Group members'!$A$2:$J$4,'Business Processes'!U$1,FALSE),"") -> Mary Johnson, Liam Chambers | V6: =IF(J6=1,VLOOKUP($E6,'Group members'!$A$2:$J$4,'Business Processes'!V$1,FALSE),"") | W6: =IF(N6=1,VLOOKUP($E6,'Group members'!$A$2:$J$4,'Business Processes'!W$1,FALSE),"") | X6: =IF(K6=1,VLOOKUP($E6,'Group members'!$A$2:$J$4,'Business Processes'!X$1,FALSE),"") -> Massimo Sigismondi | Y6: =IF(P6=1,VLOOKUP($E6,'Group members'!$A$2:$J$4,'Business Processes'!Y$1,FALSE),"") -> Ann Lewis | Z6: =IF(M6=1,VLOOKUP($E6,'Group members'!$A$2:$J$4,'Business Processes'!Z$1,FALSE),"") | AA6: =IF(O6=1,VLOOKUP($E6,'Group members'!$A$2:$J$4,'Business Processes'!AA$1,FALSE),"") -> Ronald de Wit | AB6: =IF(L6=1,VLOOKUP($E6,'Group members'!$A$2:$J$8,'Business Processes'!AB$1,FALSE),"")
A7: 5 | B7: WarehousePlus | C7: WarehousePlus-Lease | D7: Warehouse Management | E7: WarehousePlus Group | F7: Medium | G7: Medium | H7: Medium | I7: 1 | J7: 1 | L7: 1 | M7: 1 | O7: 1 | R7: =SUM(I7:Q7) -> 5 | T7: =IF(Q7=1,VLOOKUP($E7,'Group members'!$A$2:$J$4,'Business Processes'!T$1,FALSE),"") | U7: =IF(I7=1,VLOOKUP($E7,'Group members'!$A$2:$J$4,'Business Processes'!U$1,FALSE),"") -> Mary Johnson, Liam Chambers | V7: =IF(J7=1,VLOOKUP($E7,'Group members'!$A$2:$J$4,'Business Processes'!V$1,FALSE),"") -> Jaco Van Dijk | W7: =IF(N7=1,VLOOKUP($E7,'Group members'!$A$2:$J$4,'Business Processes'!W$1,FALSE),"") | X7: =IF(K7=1,VLOOKUP($E7,'Group members'!$A$2:$J$4,'Business Processes'!X$1,FALSE),"") | Y7: =IF(P7=1,VLOOKUP($E7,'Group members'!$A$2:$J$4,'Business Processes'!Y$1,FALSE),"") | Z7: =IF(M7=1,VLOOKUP($E7,'Group members'!$A$2:$J$4,'Business Processes'!Z$1,FALSE),"") -> Fernando Henriques | AA7: =IF(O7=1,VLOOKUP($E7,'Group members'!$A$2:$J$4,'Business Processes'!AA$1,FALSE),"") -> Ronald de Wit | AB7: =IF(L7=1,VLOOKUP($E7,'Group members'!$A$2:$J$8,'Business Processes'!AB$1,FALSE),"") -> Jean-Christophe Moulin
A8: 6 | B8: FinanceFast | C8: FinanceFast | D8: Manufacturing Execution | E8: FinanceFast Group | F8: Low | G8: High | H8: High | I8: 1 | O8: 1 | Q8: 1 | R8: =SUM(I8:Q8) -> 3 | T8: =IF(Q8=1,VLOOKUP($E8,'Group members'!$A$2:$J$4,'Business Processes'!T$1,FALSE),"") -> Marta Fernández, Adela Sánchez | U8: =IF(I8=1,VLOOKUP($E8,'Group members'!$A$2:$J$4,'Business Processes'!U$1,FALSE),"") -> Joanne Wright | V8: =IF(J8=1,VLOOKUP($E8,'Group members'!$A$2:$J$4,'Business Processes'!V$1,FALSE),"") | W8: =IF(N8=1,VLOOKUP($E8,'Group members'!$A$2:$J$4,'Business Processes'!W$1,FALSE),"") | X8: =IF(K8=1,VLOOKUP($E8,'Group members'!$A$2:$J$4,'Business Processes'!X$1,FALSE),"") | Y8: =IF(P8=1,VLOOKUP($E8,'Group members'!$A$2:$J$4,'Business Processes'!Y$1,FALSE),"") | Z8: =IF(M8=1,VLOOKUP($E8,'Group members'!$A$2:$J$4,'Business Processes'!Z$1,FALSE),"") | AA8: =IF(O8=1,VLOOKUP($E8,'Group members'!$A$2:$J$4,'Business Processes'!AA$1,FALSE),"") -> Sylvia Hanssen | AB8: =IF(L8=1,VLOOKUP($E8,'Group members'!$A$2:$J$8,'Business Processes'!AB$1,FALSE),"")
A9: 7 | B9: PayRoll Automation | C9: PayRoll Automation | D9: Finances Payroll | E9: PayRoll Automation Group | F9: High | G9: High | H9: High | I9: 1 | K9: 1 | N9: 1 | P9: 1 | R9: =SUM(I9:Q9) -> 4 | T9: =IF(Q9=1,VLOOKUP($E9,'Group members'!$A$2:$J$8,'Business Processes'!T$1,FALSE),"") | U9: =IF(I9=1,VLOOKUP($E9,'Group members'!$A$2:$J$8,'Business Processes'!U$1,FALSE),"") -> Elisabeth William | V9: =IF(J9=1,VLOOKUP($E9,'Group members'!$A$2:$J$8,'Business Processes'!V$1,FALSE),"") | W9: =IF(N9=1,VLOOKUP($E9,'Group members'!$A$2:$J$8,'Business Processes'!W$1,FALSE),"") -> Aita Gertsch | X9: =IF(K9=1,VLOOKUP($E9,'Group members'!$A$2:$J$8,'Business Processes'!X$1,FALSE),"") -> Fiorenzo Daza | Y9: =IF(P9=1,VLOOKUP($E9,'Group members'!$A$2:$J$8,'Business Processes'!Y$1,FALSE),"") -> Daire O'Flanagan | Z9: =IF(M9=1,VLOOKUP($E9,'Group members'!$A$2:$J$8,'Business Processes'!Z$1,FALSE),"") | AA9: =IF(O9=1,VLOOKUP($E9,'Group members'!$A$2:$J$8,'Business Processes'!AA$1,FALSE),"") | AB9: =IF(L9=1,VLOOKUP($E9,'Group members'!$A$2:$J$8,'Business Processes'!AB$1,FALSE),"")
A10: 8 | B10: Credit Check | C10: Credit Check | D10: Finances Compensation | E10: Credit Check Group | F10: Low | G10: Medium | H10: High | I10: 1 | J10: 1 | K10: 1 | L10: 1 | M10: 1 | N10: 1 | O10: 1 | P10: 1 | Q10: 1 | R10: =SUM(I10:Q10) -> 9 | T10: =IF(Q10=1,VLOOKUP($E10,'Group members'!$A$2:$J$8,'Business Processes'!T$1,FALSE),"") -> Facundo Prieto | U10: =IF(I10=1,VLOOKUP($E10,'Group members'!$A$2:$J$8,'Business Processes'!U$1,FALSE),"") -> Edie Drake | V10: =IF(J10=1,VLOOKUP($E10,'Group members'!$A$2:$J$8,'Business Processes'!V$1,FALSE),"") -> Dorian Carton | W10: =IF(N10=1,VLOOKUP($E10,'Group members'!$A$2:$J$8,'Business Processes'!W$1,FALSE),"") -> Dalina Burgdorfer | X10: =IF(K10=1,VLOOKUP($E10,'Group members'!$A$2:$J$8,'Business Processes'!X$1,FALSE),"") -> Alighiero Percoco | Y10: =IF(P10=1,VLOOKUP($E10,'Group members'!$A$2:$J$8,'Business Processes'!Y$1,FALSE),"") -> Elijah Guinness | Z10: =IF(M10=1,VLOOKUP($E10,'Group members'!$A$2:$J$8,'Business Processes'!Z$1,FALSE),"") -> Leocádia Costa | AA10: =IF(O10=1,VLOOKUP($E10,'Group members'!$A$2:$J$8,'Business Processes'!AA$1,FALSE),"") -> Sjaak Venebrugge | AB10: =IF(L10=1,VLOOKUP($E10,'Group members'!$A$2:$J$8,'Business Processes'!AB$1,FALSE),"") -> Jean-Paul Génin
A11: 9 | B11: Travel Manager | C11: Travel Manager | D11: Warehouse Management | E11: Travel Manager Group | F11: High | G11: Low | H11: High | I11: 1 | J11: 1 | L11: 1 | M11: 1 | P11: 1 | R11: =SUM(I11:Q11) -> 5 | T11: =IF(Q11=1,VLOOKUP($E11,'Group members'!$A$2:$J$8,'Business Processes'!T$1,FALSE),"") | U11: =IF(I11=1,VLOOKUP($E11,'Group members'!$A$2:$J$8,'Business Processes'!U$1,FALSE),"") -> Shayla Moss | V11: =IF(J11=1,VLOOKUP($E11,'Group members'!$A$2:$J$8,'Business Processes'!V$1,FALSE),"") -> Jérémie Marissens | W11: =IF(N11=1,VLOOKUP($E11,'Group members'!$A$2:$J$8,'Business Processes'!W$1,FALSE),"") | X11: =IF(K11=1,VLOOKUP($E11,'Group members'!$A$2:$J$8,'Business Processes'!X$1,FALSE),"") | Y11: =IF(P11=1,VLOOKUP($E11,'Group members'!$A$2:$J$8,'Business Processes'!Y$1,FALSE),"") -> Zac O'Friel | Z11: =IF(M11=1,VLOOKUP($E11,'Group members'!$A$2:$J$8,'Business Processes'!Z$1,FALSE),"") -> Letícia Pires | AA11: =IF(O11=1,VLOOKUP($E11,'Group members'!$A$2:$J$8,'Business Processes'!AA$1,FALSE),"") | AB11: =IF(L11=1,VLOOKUP($E11,'Group members'!$A$2:$J$8,'Business Processes'!AB$1,FALSE),"") -> Iseult Girard
A12: 10 | B12: HolidayPlanner | C12: HolidayPlanner | D12: Recipes Management | E12: HolidayPlanner Group | F12: Low | G12: Low | H12: High | I12: 1 | J12: 1 | K12: 1 | L12: 1 | M12: 1 | N12: 1 | O12: 1 | P12: 1 | Q12: 1 | R12: =SUM(I12:Q12) -> 9 | T12: =IF(Q12=1,VLOOKUP($E12,'Group members'!$A$2:$J$8,'Business Processes'!T$1,FALSE),"") -> Laureano Velasco | U12: =IF(I12=1,VLOOKUP($E12,'Group members'!$A$2:$J$8,'Business Processes'!U$1,FALSE),"") -> Patricia Mosley | V12: =IF(J12=1,VLOOKUP($E12,'Group members'!$A$2:$J$8,'Business Processes'!V$1,FALSE),"") -> Jonathan Dervaux | W12: =IF(N12=1,VLOOKUP($E12,'Group members'!$A$2:$J$8,'Business Processes'!W$1,FALSE),"") -> Mathilde Dettling | X12: =IF(K12=1,VLOOKUP($E12,'Group members'!$A$2:$J$8,'Business Processes'!X$1,FALSE),"") -> Sabele Vivenzio | Y12: =IF(P12=1,VLOOKUP($E12,'Group members'!$A$2:$J$8,'Business Processes'!Y$1,FALSE),"") -> Aleksander Muldowney | Z12: =IF(M12=1,VLOOKUP($E12,'Group members'!$A$2:$J$8,'Business Processes'!Z$1,FALSE),"") -> Custódia Valente | AA12: =IF(O12=1,VLOOKUP($E12,'Group members'!$A$2:$J$8,'Business Processes'!AA$1,FALSE),"") -> Walter van den Kerkdijk | AB12: =IF(L12=1,VLOOKUP($E12,'Group members'!$A$2:$J$8,'Business Processes'!AB$1,FALSE),"") -> Sarah Astier

Sheet Security
A1: Applicatio ID | B1: Main application | C1: Sub application | D1: GDPR | E1: DATA PROCESOR | F1: Confidentality | G1: Integrity | H1: Availability
A2: 1 | B2: My TimeTrack | C2: My TimeTrack | D2: YES | F2: High | G2: High | H2: 0.95
A3: 2 | B3: WarehousePlus | C3: WarehousePlus-Facilities | D3: NO | F3: Medium | G3: Medium | H3: 0.8
A4: 3 | B4: WarehousePlus | C4: WarehousePlus-Promotions | D4: NO | F4: Medium | G4: Medium | H4: 0.8
A5: 4 | B5: WarehousePlus | C5: WarehousePlus-IT | D5: NO | F5: Medium | G5: Medium | H5: 0.8
A6: 5 | B6: WarehousePlus | C6: WarehousePlus-Lease | D6: NO | F6: Medium | G6: Low | H6: 0.8
A7: 6 | B7: FinanceFast | C7: FinanceFast | D7: YES | F7: High | G7: High | H7: 0.9
A8: 7 | B8: PayRoll Automation | C8: PayRoll Automation | D8: YES | F8: High | G8: High | H8: 0.95
A9: 8 | B9: Credit Check | C9: Credit Check | D9: YES | F9: High | G9: High | H9: 0.95
A10: 9 | B10: Travel Manager | C10: Travel Manager | D10: NO | F10: High | G10: High | H10: 0.9
A11: 10 | B11: HolidayPlanner | C11: HolidayPlanner | D11: YES | F11: High | G11: High | H11: 0.9

Sheet Audit Compliance
A1: Applicatio ID | B1: Main application | C1: Sub application | D1: In scope | E1: User management | F1: Status (findings)
A2: 1 | B2: My TimeTrack | C2: My TimeTrack | D2: YES | E2: Auditor 1
A3: 2 | B3: WarehousePlus | C3: WarehousePlus-Facilities | D3: NO
A4: 3 | B4: WarehousePlus | C4: WarehousePlus-Promotions | D4: NO
A5: 4 | B5: WarehousePlus | C5: WarehousePlus-IT | D5: NO
A6: 5 | B6: WarehousePlus | C6: WarehousePlus-Lease | D6: NO
A7: 6 | B7: FinanceFast | C7: FinanceFast | D7: YES | E7: Auditor 2
A8: 7 | B8: PayRoll Automation | C8: PayRoll Automation | D8: YES | E8: Auditor 2
A9: 8 | B9: Credit Check | C9: Credit Check | D9: YES | E9: Auditor 2
A10: 9 | B10: Travel Manager | C10: Travel Manager | D10: YES | E10: Auditor 3
A11: 10 | B11: HolidayPlanner | C11: HolidayPlanner | D11: NO

Sheet Infrastructure
A1: Applicatio ID | B1: Main application | C1: Sub application | D1: Servers | E1: Network | F1: Other CI
A2: 1 | B2: My TimeTrack | C2: My TimeTrack | D2: SRV-00001, DB-ES234 | E2: F5-00133
A3: 2 | B3: WarehousePlus | C3: WarehousePlus-Facilities | D3: ESDATA-WS001, ESDATA-WS002, ESDATA-DB009 | E3: LB-004
A4: 3 | B4: WarehousePlus | C4: WarehousePlus-Promotions | D4: ESDATA-WS008, ESDATA-WS009, ESDATA-DB004 | E4: LB-020
A5: 4 | B5: WarehousePlus | C5: WarehousePlus-IT | D5: ESDATA-WS007, ESDATA-DB007 | E5: LB-050
A6: 5 | B6: WarehousePlus | C6: WarehousePlus-Lease | D6: ESDATA-WS006, ESDATA-DB006 | E6: LB-008
A7: 6 | B7: FinanceFast | C7: FinanceFast | D7: ESDATA-WS003, ESDATA-DB002 | E7: F5-00326
A8: 7 | B8: PayRoll Automation | C8: PayRoll Automation | D8: ESDATA-WS004, ESDATA-DB003 | E8: F5-00441
A9: 8 | B9: Credit Check | C9: Credit Check | D9: ESDATA-WS005, ESDATA-DB005 | E9: F5-00223
A10: 9 | B10: Travel Manager | C10: Travel Manager | D10: ESDATA-WS042, ESDATA-WS072, ESDATA-DB052, DEV ESDATA-DB042 | E10: LB-444
A11: 10 | B11: HolidayPlanner | C11: HolidayPlanner | D11: ESDATA-WS040, ESDATA-WS070, ESDATA-DB050, DEV ESDATA-DB040 | E11: F5-00189

Sheet Health
A1: Applicatio ID | B1: Main application | C1: Sub application | D1: Version | E1: Software provider | F1: Support Partner | G1: Obsolete | H1: Health | I1: Risk | J1: Satisfaction | K1: Annual License cost | L1: Annual Maintenance Cost | M1: Internal FTE
A2: 1 | B2: My TimeTrack | C2: My TimeTrack | G2: No | H2: Good
A3: 2 | B3: WarehousePlus | C3: WarehousePlus-Facilities | F3: WHF | G3: Yes | H3: Low | I3: High | J3: Low
A4: 3 | B4: WarehousePlus | C4: WarehousePlus-Promotions | F4: WHF | G4: Yes | H4: Low | I4: High | J4: Low
A5: 4 | B5: WarehousePlus | C5: WarehousePlus-IT | F5: WHF | G5: Yes | H5: Low | I5: High | J5: Low
A6: 5 | B6: WarehousePlus | C6: WarehousePlus-Lease | F6: WHF | G6: Yes | H6: Low | I6: High | J6: Low
A7: 6 | B7: FinanceFast | C7: FinanceFast | G7: No | H7: Good
A8: 7 | B8: PayRoll Automation | C8: PayRoll Automation | G8: No | H8: Good | I8: High | J8: Low
A9: 8 | B9: Credit Check | C9: Credit Check | G9: No | H9: Good
A10: 9 | B10: Travel Manager | C10: Travel Manager | F10: BBTH | G10: No | H10: Good
A11: 10 | B11: HolidayPlanner | C11: HolidayPlanner | G11: No | H11: Good
I1048576: High

Sheet Group members
A1: GROUP | B1: FR | C1: ES | D1: UK | E1: BE | F1: CH | G1: IT | H1: IR | I1: PT | J1: NL
A2: My TimeTrack Group | B2: Anne-Marie Lavigne | C2: Gonzalo Santos, Marga González | D2: John Anderson | E2: Karel De Jong | F2: Michael Fowkes | G2: Luigi Pennini | H2: Jean McCallister | I2: Joao Ereio | J2: Jan Hakvoort
A3: WarehousePlus Group | B3: Jean-Christophe Moulin | C3: Lourdes García | D3: Mary Johnson, Liam Chambers | E3: Jaco Van Dijk | F3: Donald Krieger | G3: Massimo Sigismondi | H3: Ann Lewis | I3: Fernando Henriques | J3: Ronald de Wit
A4: FinanceFast Group | B4: Amélie Laurent | C4: Marta Fernández, Adela Sánchez | D4: Joanne Wright | E4: Matthijs Visser | F4: Alexandre Bieri | G4: Giulio Moranti | H4: Catherine Martins | I4: Sofia Fernandes | J4: Sylvia Hanssen
A5: PayRoll Automation Group | B5: Jérémy Héroux | C5: Luis Cambil, Fernando Hernández | D5: Elisabeth William | E5: Martin Demeyere | F5: Aita Gertsch | G5: Fiorenzo Daza | H5: Daire O'Flanagan | I5: Micaela Vomlel | J5: Florentijn Manenberg
A6: Credit Check Group | B6: Jean-Paul Génin | C6: Facundo Prieto | D6: Edie Drake | E6: Dorian Carton | F6: Dalina Burgdorfer | G6: Alighiero Percoco | H6: Elijah Guinness | I6: Leocádia Costa | J6: Sjaak Venebrugge
A7: Travel Manager Group | B7: Iseult Girard | C7: Yolanda Bravo | D7: Shayla Moss | E7: Jérémie Marissens | F7: Valentina Favre | G7: Frido Scanga | H7: Zac O'Friel | I7: Letícia Pires | J7: Remko Adriaanse
A8: HolidayPlanner Group | B8: Sarah Astier | C8: Laureano Velasco | D8: Patricia Mosley | E8: Jonathan Dervaux | F8: Mathilde Dettling | G8: Sabele Vivenzio | H8: Aleksander Muldowney | I8: Custódia Valente | J8: Walter van den Kerkdijk
